polars_encryption-0.1.5.dist-info/METADATA
polars_encryption-0.1.5.dist-info/WHEEL
polars_encryption-0.1.5.dist-info/licenses/LICENSE
polars_encryption/__init__.py
polars_encryption/utils.py
polars_encryption/polars_encryption.abi3.so
polars_encryption-0.1.5.dist-info/RECORD
